orbis_plugin_aggregation_serial_corpus/__init__.py
orbis_plugin_aggregation_serial_corpus/main.py
orbis_plugin_aggregation_serial_corpus-2.2.4.dist-info/LICENSE
orbis_plugin_aggregation_serial_corpus-2.2.4.dist-info/METADATA
orbis_plugin_aggregation_serial_corpus-2.2.4.dist-info/WHEEL
orbis_plugin_aggregation_serial_corpus-2.2.4.dist-info/top_level.txt
orbis_plugin_aggregation_serial_corpus-2.2.4.dist-info/RECORD
