Metadata-Version: 2.1
Name: orbis-plugin-aggregation-serial-corpus
Version: 2.2.4
Summary: The serial_corpus aggregation plugin for Orbis
Home-page: https://github.com/orbis-eval/orbis_plugin_aggregation_serial_corpus
Author: fabod
License: GPL2
Platform: UNKNOWN
Requires-Python: >3.6
